llama_index/readers/hubspot/__init__.py
llama_index/readers/hubspot/base.py
llama_index_readers_hubspot-0.4.1.dist-info/METADATA
llama_index_readers_hubspot-0.4.1.dist-info/WHEEL
llama_index_readers_hubspot-0.4.1.dist-info/licenses/LICENSE
llama_index_readers_hubspot-0.4.1.dist-info/RECORD
