Metadata-Version: 2.4
Name: llama-index-readers-hubspot
Version: 0.4.1
Summary: llama-index readers hubspot integration
Author-email: Your Name <you@example.com>
Maintainer: ykhli
License-Expression: MIT
License-File: LICENSE
Keywords: hubspot
Requires-Python: <4.0,>=3.9
Requires-Dist: hubspot-api-client<9,>=8.2.1
Requires-Dist: llama-index-core<0.15,>=0.13.0
